yt_scrape/__init__.py
yt_scrape/exceptions.py
yt_scrape/scraper.py
yt_scrape/utils.py
youtube_webscrape_api-0.0.3.dist-info/LICENSE.md
youtube_webscrape_api-0.0.3.dist-info/METADATA
youtube_webscrape_api-0.0.3.dist-info/WHEEL
youtube_webscrape_api-0.0.3.dist-info/top_level.txt
youtube_webscrape_api-0.0.3.dist-info/RECORD
