Metadata-Version: 2.1
Name: youtube-webscrape-api
Version: 0.0.3
Summary: Webscrape based youtube api, free of cost
Home-page: https://github.com/huzai786/Youtube-Scraper
Author: Muhammad Huzaifa
Author-email: muhammadhuzaifagamer123@gmail.com
License: MIT
Keywords: youtube-api,youtube-scraper,Youtube-scrape
Classifier: Programming Language :: Python :: 3.7
Classifier: Programming Language :: Python :: 3.8
Classifier: Programming Language :: Python :: 3.9
Classifier: Programming Language :: Python :: 3.10
Classifier: Operating System :: OS Independent
Classifier: License :: OSI Approved :: MIT License
Classifier: Intended Audience :: Developers
License-File: LICENSE.md
Requires-Dist: lxml
Requires-Dist: beautifulsoup4
Requires-Dist: requests
Requires-Dist: fake-useragent
